slopbox/__init__.py
slopbox/app.py
slopbox/base.py
slopbox/claude.py
slopbox/cli.py
slopbox/fastapi.py
slopbox/genimg.py
slopbox/model.py
slopbox/replicate.py
slopbox/ui.py
slopbox/videosync.py
slopbox/image/__init__.py
slopbox/image/gallery.py
slopbox/image/img.py
slopbox/image/slideshow.py
slopbox/image/spec.py
slopbox/pageant/__init__.py
slopbox/pageant/model.py
slopbox/pageant/routes.py
slopbox/pageant/ui.py
slopbox/prompt/__init__.py
slopbox/prompt/form.py
slopbox-0.6.dist-info/METADATA
slopbox-0.6.dist-info/WHEEL
slopbox-0.6.dist-info/entry_points.txt
slopbox-0.6.dist-info/RECORD
