Metadata-Version: 2.4
Name: slopbox
Version: 0.6
Summary: AI image generation platform and video-audio synchronization tool with real-time waveform visualization
Project-URL: Homepage, https://github.com/mbrock/slopbox
Project-URL: Issues, https://github.com/mbrock/slopbox/issues
Author-email: Mikael Brockman <mikael@brockman.se>
License-Expression: MIT
Keywords: ai,fastapi,image-generation,web-app
Classifier: Development Status :: 4 - Beta
Classifier: Environment :: Web Environment
Classifier: Framework :: FastAPI
Classifier: Intended Audience :: End Users/Desktop
Classifier: License :: OSI Approved :: MIT License
Classifier: Programming Language :: Python :: 3
Classifier: Programming Language :: Python :: 3.13
Classifier: Topic :: Internet :: WWW/HTTP :: Dynamic Content
Classifier: Topic :: Multimedia :: Graphics
Requires-Python: >=3.13
Requires-Dist: aiofiles>=24.1.0
Requires-Dist: aiohttp>=3.11.16
Requires-Dist: anthropic>=0.46.0
Requires-Dist: anyio>=4.8.0
Requires-Dist: click>=8.0.0
Requires-Dist: fastapi[standard]>=0.115.8
Requires-Dist: openai>=1.70.0
Requires-Dist: pillow>=11.1.0
Requires-Dist: pytest-asyncio>=0.25.3
Requires-Dist: pytest-xdist[psutil]>=3.7.0
Requires-Dist: replicate>=1.0.4
Requires-Dist: tagflow>=0.7.0
Requires-Dist: uvicorn[standard]>=0.34.0
Provides-Extra: dev
Requires-Dist: black>=24.1.0; extra == 'dev'
Requires-Dist: httpx>=0.25.0; extra == 'dev'
Requires-Dist: isort>=5.13.0; extra == 'dev'
Requires-Dist: mypy>=1.8.0; extra == 'dev'
Requires-Dist: pytest-asyncio>=0.23.0; extra == 'dev'
Requires-Dist: pytest>=8.0.0; extra == 'dev'
Requires-Dist: ruff>=0.2.0; extra == 'dev'
